{
    "enabled": true,
    "neededInstalledMods": [],
    "neededUninstalledMods": [],
    "spawns": [
        {
            "id": "maractaya-1",
            "pokemon": "maractaya",
            "type": "pokemon",
            "context": "grounded",
            "bucket": "common",
            "level": "18-49",
            "weight": 0.6,
            "condition": {
                "canSeeSky": true,
                "biomes": [
                    "#cobblemon:is_jungle"
                ]
            }
        },
        {
            "id": "maractaya-2",
            "pokemon": "maractaya",
            "type": "pokemon",
            "context": "grounded",
            "bucket": "uncommon",
            "level": "18-49",
            "weight": 0.6,
            "condition": {
                "canSeeSky": true,
                "biomes": [
                    "#cobblemon:is_sandy"
                ]
            }
        }
    ]
}